[
    {
      "condition": "minecraft:all_of",
      "terms": [
        {
          "condition": "minecraft:location_check",
          "predicate": {
            "block": {
              "blocks": [
                "minecraft:repeater"
              ]
            }
          }
        },
        {
          "condition": "minecraft:location_check",
          "offsetY": -1,
          "predicate": {
            "block": {
              "blocks": [
                "minecraft:redstone_lamp"
              ]
            }
          }
        }
      ]
    }
  ]
  